{"itemno":105019,"headline":"SCHOTT ZERODUR GROUND BLANKS","description":"320mm x 262mm x 18mm","mfr":"Schott","model":"","price":"Best Price","qty":18,"location":"Scotia, NY US","category":"Other Optical / Photonic Equipment","keywords":"","unixTimeStamp":1232449554,"popular":14,"isFeatured":0,"categories.lvl0":"Optical / Photonic Equipment","categories.lvl1":"Optical / Photonic Equipment > Other Optical / Photonic Equipment","specstable":"<table border=\"0\" cellpadding=\"2\"><tr class=\"cell\"><td class=\"txtb\">Manufacturer </td><td class=\"txt\">Schott</td></tr><tr class=\"alt\"><td class=\"txtb\">Description </td><td class=\"txt\">Ground Blanks </td></tr><tr class=\"cell\"><td class=\"txtb\">Other Information </td><td class=\"txt\"><p>Part number: 1541-801-963<br />Melt: F 9979 LK 7179<br />Item: #12D 8414G</p></td></tr><tr class=\"alt\" ><td class=\"txtb\">Exterior Dimensions </td><td> </td></tr><tr class=\"cell\"><td class=\"txt\"> Width </td><td>12.598 in (32.0 cm)</td></tr><tr class=\"alt\"><td class=\"txt\"> Depth </td><td>10.315 in (26.2 cm)</td></tr><tr class=\"cell\"><td class=\"txt\"> Height </td><td>0.709 in (1.8 cm)</td></tr><tr class=\"alt\"><td class=\"txtb\">Weight </td><td class=\"txt\">10 lb (5 kg)</td></tr> </table>","imgbase":"https://www.capovani.com/clientresources/","imgMain":"107/108/74/63174/105019-a-Schott_GroundBlank_main_i105019.jpg","imagesXtra":["107/108/74/63174/105019-1-Schott_GroundBlank_large_i105019.jpg"]}