{"itemno":110165,"headline":"INFICON RESIDUAL GAS ANALYZER SYSTEM","description":"Residual Gas Analyzer System    Inficon Transpector CIS","mfr":"Inficon","model":"Transpector CIS","price":"Best Price","qty":1,"location":"Scotia, NY US","category":"Residual Gas Analyzers","keywords":"rga  amu","unixTimeStamp":1242838084,"popular":5,"isFeatured":0,"categories.lvl0":"Vacuum Processing Equipment","categories.lvl1":"Vacuum Processing Equipment > Vacuum Process Instrumentation","categories.lvl2":"Vacuum Processing Equipment  >  Vacuum Process Instrumentation > Residual Gas Analyzers","specstable":"<table border=\"0\" cellpadding=\"2\"><tr class=\"cell\"><td class=\"txtb\">Manufacturer </td><td class=\"txt\">Inficon</td></tr><tr class=\"alt\"><td class=\"txtb\">Model </td><td class=\"txt\">Transpector CIS </td></tr><tr class=\"cell\"><td class=\"txtb\">Description </td><td class=\"txt\">Residual Gas Analyzer </td></tr><tr class=\"alt\"><td class=\"txtb\">Mass Range </td><td class=\"txt\">200 AMU</td></tr><tr class=\"cell\"><td class=\"txtb\">Accessories </td><td class=\"txt\"><ul><li>CIS TS200</li><li>CIS Controller Part number 90B-140-G1</li><li>Leybold 151 Turbo pump with NT 150/360 controller</li><li>IG3 Vacuum Gauge Controller</li><li>4 Position Manual Sample Valve</li><li>Leybold D1.6B</li></ul></td></tr><tr class=\"alt\"><td class=\"txtb\">Other Information </td><td class=\"txt\"><p>Mass Range: 200 AMU<br /> RS232 and RS485<br />TWare32 software p/n 911-339-G3, will work with Windows XP<br />As of 2015 Inficon is not supporting Tware32 and giving software for free<br /> Foreline pump is not included</p></td></tr><tr class=\"cell\" ><td class=\"txtb\">Power Requirements </td><td class=\"txt\">110 V 15.0 A 60 Hz 1 Phase</td></tr><tr class=\"alt\"><td class=\"txtb\">CE Marked </td><td class=\"txt\">YES</td></tr><tr class=\"cell\" ><td class=\"txtb\">Exterior Dimensions </td><td> </td></tr><tr class=\"alt\"><td class=\"txt\"> Width </td><td>39.000 in (99.1 cm)</td></tr><tr class=\"cell\"><td class=\"txt\"> Depth </td><td>22.000 in (55.9 cm)</td></tr><tr class=\"alt\"><td class=\"txt\"> Height </td><td>62.000 in (157.5 cm)</td></tr><tr class=\"cell\"><td class=\"txtb\">Weight </td><td class=\"txt\">334 lb (152 kg)</td></tr> </table>","imgbase":"https://www.capovani.com/clientresources/","imgMain":"107/108/88/188/110165-a-Inficon_TranspectorCIS_main_i110165.jpg","imagesXtra":["107/108/88/188/110165-1-Inficon_TranspectorCIS_large_i110165.jpg","107/108/88/188/110165-2-Inficon_TranspectorCIS_detail1_i110165.jpg","107/108/88/188/110165-3-Inficon_TranspectorCIS_detail2_i110165.jpg","107/108/88/188/110165-4-Inficon_TranspectorCIS_detail3_i110165.jpg"]}