{"itemno":124793,"headline":"NEWPORT BALL BEARING LINEAR STAGE","description":"Ball Bearing Linear Stage","mfr":"Newport","model":"460P-XY","price":"$330.00","qty":1,"location":"Scotia, NY US","category":"Optical Components","keywords":"damp rods jacks rods mirror holders mounts plates posts gimble lens mount rail carrier adpter clamp base bracket diaphrams carriers","unixTimeStamp":1280745518,"popular":0,"isFeatured":0,"categories.lvl0":"Optical / Photonic Equipment","categories.lvl1":"Optical / Photonic Equipment > Optical Components","specstable":"<table border=\"0\" cellpadding=\"2\"><tr class=\"cell\"><td class=\"txtb\">Manufacturer </td><td class=\"txt\">Newport</td></tr><tr class=\"alt\"><td class=\"txtb\">Model </td><td class=\"txt\">460P-XY </td></tr><tr class=\"cell\"><td class=\"txtb\">Type </td><td class=\"txt\">Ball Bearing Linear Stage </td></tr><tr class=\"alt\"><td class=\"txtb\">Other Information </td><td class=\"txt\"><p>Axes of Travel: XY<br /> Travel: 1.00 in<br /> Load Capacity: 15 lb<br /> Load Capacity (Vertical): 5 lb<br /> Thread Type: English</p></td></tr> </table>","imgbase":"https://www.capovani.com/clientresources/","imgMain":"no-image.png","imagesXtra":[]}