{"itemno":140291,"headline":"MKS INSTRUMENTS DEVICENET TO RS232 GATEWAYS","description":"DeviceNet to RS232 Gateways","mfr":"MKS Instruments","model":"CDN 466","price":"$200.00","qty":2,"location":"Scotia, NY US","category":"Other Vacuum Instrumentation","keywords":"","unixTimeStamp":1326189543,"popular":0,"isFeatured":0,"categories.lvl0":"Vacuum Processing Equipment","categories.lvl1":"Vacuum Processing Equipment > Vacuum Process Instrumentation","categories.lvl2":"Vacuum Processing Equipment  >  Vacuum Process Instrumentation > Other Vacuum Instrumentation","specstable":"<table border=\"0\" cellpadding=\"2\"><tr class=\"cell\"><td class=\"txtb\">Manufacturer </td><td class=\"txt\">MKS Instruments</td></tr><tr class=\"alt\"><td class=\"txtb\">Model </td><td class=\"txt\">CDN 466 </td></tr><tr class=\"cell\"><td class=\"txtb\">Description </td><td class=\"txt\">Devicenet to RS232 Gateways </td></tr><tr class=\"alt\" ><td class=\"txtb\">Exterior Dimensions </td><td> </td></tr><tr class=\"cell\"><td class=\"txt\"> Width </td><td>4.500 in (11.4 cm)</td></tr><tr class=\"alt\"><td class=\"txt\"> Depth </td><td>3.250 in (8.3 cm)</td></tr><tr class=\"cell\"><td class=\"txt\"> Height </td><td>1.000 in (2.5 cm)</td></tr><tr class=\"alt\"><td class=\"txtb\">Weight </td><td class=\"txt\">1 lb (0 kg)</td></tr> </table>","imgbase":"https://www.capovani.com/clientresources/","imgMain":"107/108/45/1045/140291-a-MKS_CDN466_main_i140291.jpg","imagesXtra":["107/108/45/1045/140291-1-MKS_CDN466_large_i140291.jpg","107/108/45/1045/140291-2-MKS_CDN466_detail1_i140291.jpg","107/108/45/1045/140291-3-MKS_CDN466_detail2_i140291.jpg"]}