{"itemno":140782,"headline":"ELECTRONIC MEASUREMENTS INC. DIRECT CURRENT POWER SUPPLY 10 V, 90 A","description":"Direct Current Power Supply","mfr":"Electronic Measuremt","model":"TCR 10S90","price":"$999.00","qty":1,"location":"Scotia, NY US","category":"DC Power Supplies","keywords":"dc","unixTimeStamp":1327490062,"popular":0,"isFeatured":0,"categories.lvl0":"Test & Measurement Equipment","categories.lvl1":"Test & Measurement Equipment > Power Supplies","categories.lvl2":"Test & Measurement Equipment  >  Power Supplies > DC Power Supplies","specstable":"<table border=\"0\" cellpadding=\"2\"><tr class=\"cell\"><td class=\"txtb\">Manufacturer </td><td class=\"txt\">Electronic Measuremt</td></tr><tr class=\"alt\"><td class=\"txtb\">Model </td><td class=\"txt\">TCR 10S90 </td></tr><tr class=\"cell\"><td class=\"txtb\">Maximum Output Voltage </td><td class=\"txt\">10.00 Volts</td></tr><tr class=\"alt\"><td class=\"txtb\">Maximum Output Current </td><td class=\"txt\">90.00 Amps</td></tr><tr class=\"cell\"><td class=\"txtb\">Maximum Output Power </td><td class=\"txt\">0.90 kW</td></tr><tr class=\"alt\" ><td class=\"txtb\">Regulation Modes </td><td class=\"txt\">Constant Current Constant Voltage</td></tr><tr class=\"cell\"><td class=\"txtb\">Ripple </td><td class=\"txt\">80 mV </td></tr><tr class=\"alt\"><td class=\"txtb\">Panel Meters </td><td class=\"txt\">Analog</td></tr><tr class=\"cell\"><td class=\"txtb\">External Cooling </td><td class=\"txt\">Forced Air Cooled</td></tr><tr class=\"alt\"><td class=\"txtb\">Other Information </td><td class=\"txt\"><ul><li>1.8 kW</li><li>Regulation: 0.1%</li><li>Stability: 0.05%</li><li>Over-temp and over-voltage protection</li><li>Transient response: 30% load change will recover to 2% within 75 milliseconds<p><a href=\"http://www.us.tdk-lambda.com/hp/pdfs/Product_manuals/83470001rE.pdf\" target=\"_blank\" rel=\"noopener noreferrer\">Click here for the manual</a></p></li></ul></td></tr><tr class=\"cell\" ><td class=\"txtb\">Power Requirements </td><td class=\"txt\">105-125 V 50/60 Hz 1 Phase</td></tr><tr class=\"alt\"><td class=\"txtb\">Condition </td><td class=\"txt\">Very Good</td></tr><tr class=\"cell\" ><td class=\"txtb\">Exterior Dimensions </td><td> </td></tr><tr class=\"alt\"><td class=\"txt\"> Width </td><td>19.000 in (48.3 cm)</td></tr><tr class=\"cell\"><td class=\"txt\"> Depth </td><td>21.000 in (53.3 cm)</td></tr><tr class=\"alt\"><td class=\"txt\"> Height </td><td>3.500 in (8.9 cm)</td></tr><tr class=\"cell\"><td class=\"txtb\">Weight </td><td class=\"txt\">64 lb (29 kg)</td></tr> </table>","imgbase":"https://www.capovani.com/clientresources/","imgMain":"107/108/65/365/140782-a-EMI_TCR-10S90_main_i140782.jpg","imagesXtra":["107/108/65/365/140782-1-EMI_TCR-10S90_large_i140782.jpg","107/108/65/365/140782-2-EMI_TCR-10S90_detail1_i140782.jpg"]}