{"itemno":142915,"headline":"DAIHEN RF AUTO MATCHING NETWORK","description":"Matching Network","mfr":"Daihen","model":"RMN-30F9","price":"Best Price","qty":1,"location":"Scotia, NY US","category":"Matching Networks","keywords":"","unixTimeStamp":1334056045,"popular":1,"isFeatured":1,"categories.lvl0":"Test & Measurement Equipment","categories.lvl1":"Test & Measurement Equipment > Radio Frequency (RF) Equipment","categories.lvl2":"Test & Measurement Equipment  >  Radio Frequency (RF) Equipment > Matching Networks","specstable":"<table border=\"0\" cellpadding=\"2\"><tr class=\"cell\"><td class=\"txtb\">Manufacturer </td><td class=\"txt\">Daihen</td></tr><tr class=\"alt\"><td class=\"txtb\">Model </td><td class=\"txt\">RMN-30F9 </td></tr><tr class=\"cell\"><td class=\"txtb\">Power Capacity </td><td class=\"txt\">3.0 kW</td></tr><tr class=\"alt\"><td class=\"txtb\">Maximum </td><td class=\"txt\">13.56</td></tr><tr class=\"cell\"><td class=\"txtb\">Scale </td><td class=\"txt\">MHz</td></tr><tr class=\"alt\"><td class=\"txtb\">Controller Type </td><td class=\"txt\">Analog</td></tr><tr class=\"cell\"><td class=\"txtb\">External Cooling </td><td class=\"txt\">Water Cooled</td></tr><tr class=\"alt\"><td class=\"txtb\">Other Information </td><td class=\"txt\">Matching accuracy: Within 0.5% (power ratio)<br /> Matching Speed: Within 3 s<br /> Max Power: 3000 W<br /> RS 232C<br /> Match network: Model RMN-30F9<br /> Controller: Model MCB-10<br /> Remote Control: Model CMC-10</td></tr><tr class=\"cell\"><td class=\"txtb\">Weight </td><td class=\"txt\">66 lb (30 kg)</td></tr> </table>","imgbase":"https://www.capovani.com/clientresources/","imgMain":"107/108/98/998/142915-a-Daihen_RMN-30F9_main2_i142915.jpg","imagesXtra":["107/108/98/998/142915-1-Daihen_RMN-30F9_large_i142915.jpg","107/108/98/998/142915-2-Daihen_RMN-30F9_detail1_i142915.jpg","107/108/98/998/142915-3-Daihen_RMN-30F9_detail2_i142915.jpg","107/108/98/998/142915-4-Daihen_RMN-30F9_detail3_i142915.jpg","107/108/98/998/142915-5-Daihen_RMN-30F9_detail4_i142915.jpg","107/108/98/998/142915-6-Daihen_RMN-30F9_detail5_i142915.jpg","107/108/98/998/142915-7-Daihen_RMN-30F9_detail6_i142915.jpg","107/108/98/998/142915-8-Daihen_RMN-30F9_detail7_i142915.jpg","107/108/98/998/142915-9-Daihen_RMN-30F9_detail8_i142915.jpg","107/108/98/998/142915-10-Daihen_RMN-30F9_detail9_i142915.jpg"]}