{"itemno":147408,"headline":"VAT VACUUM ANGLE VALVE, KF 16","description":"Manual Angle Valve, 90&deg;","mfr":"VAT","model":"26424-KA01","price":"$120.00","qty":1,"location":"Scotia, NY US","category":"Vacuum Angle Valves","keywords":"","unixTimeStamp":1338472524,"popular":0,"isFeatured":0,"specstable":"<table border=\"0\" cellpadding=\"2\"><tr class=\"cell\"><td class=\"txtb\">Manufacturer </td><td class=\"txt\">VAT</td></tr><tr class=\"alt\"><td class=\"txtb\">Model </td><td class=\"txt\">26424-KA01 </td></tr><tr class=\"cell\"><td class=\"txtb\">Valve Angle </td><td class=\"txt\">90°</td></tr><tr class=\"alt\"><td class=\"txtb\">Valve Actuation </td><td class=\"txt\">Manual</td></tr><tr class=\"cell\"><td class=\"txtb\">Flange Type </td><td class=\"txt\">KF</td></tr><tr class=\"alt\"><td class=\"txtb\">Flange Size </td><td class=\"txt\">16.00 mm (0.63 in)</td></tr><tr class=\"cell\"><td class=\"txtb\">Valve Material </td><td class=\"txt\">Aluminum</td></tr><tr class=\"alt\"><td class=\"txtb\">CE Marked </td><td class=\"txt\">YES</td></tr><tr class=\"cell\" ><td class=\"txtb\">Exterior Dimensions </td><td> </td></tr><tr class=\"alt\"><td class=\"txt\"> Width </td><td>1.500 in (3.8 cm)</td></tr><tr class=\"cell\"><td class=\"txt\"> Depth </td><td>2.500 in (6.4 cm)</td></tr><tr class=\"alt\"><td class=\"txt\"> Height </td><td>4.120 in (10.5 cm)</td></tr><tr class=\"cell\"><td class=\"txtb\">Weight </td><td class=\"txt\">1 lb (0 kg)</td></tr> </table>","imgbase":"https://www.capovani.com/clientresources/","imgMain":"107/108/21/1621/147408-a-VAT_26424-KA01_main_i147408.jpg","imagesXtra":["107/108/21/1621/147408-1-VAT_26424-KA01_large_i147408.jpg"]}