{"itemno":148799,"headline":"MKS CAPACITANCE GAUGE 10 TORR","description":"Capacitance Gauge","mfr":"MKS Instruments, Inc","model":"122A-11063","price":"$400.00","qty":1,"location":"Scotia, NY US","category":"Capacitance Gauges","keywords":"Baratron manometer","unixTimeStamp":1342167799,"popular":2,"isFeatured":0,"specstable":"<table border=\"0\" cellpadding=\"2\"><tr class=\"cell\"><td class=\"txtb\">Manufacturer </td><td class=\"txt\">MKS Instruments, Inc</td></tr><tr class=\"alt\"><td class=\"txtb\">Model </td><td class=\"txt\">122A-11063 </td></tr><tr class=\"cell\"><td class=\"txtb\">Description </td><td class=\"txt\">Baratron Capacitance Gauge </td></tr><tr class=\"alt\"><td class=\"txtb\">Pressure Range </td><td class=\"txt\">10.00 torr (13.33 mbar)</td></tr><tr class=\"cell\" ><td class=\"txtb\">Connection </td><td class=\"txt\"><span class=\"note\"><b><i>Type:</i></b></span></span> VCR <span class=\"note\"><b><i>Size:</i></b></span> 8 </td></tr><tr class=\"alt\"><td class=\"txtb\">Other Information </td><td class=\"txt\">Pressure range: 10 Torr<br />Input voltage: 15 VDC<br />Output voltage: 0-10 VDC</td></tr><tr class=\"cell\" ><td class=\"txtb\">Exterior Dimensions </td><td> </td></tr><tr class=\"alt\"><td class=\"txt\"> Width </td><td>3.000 in (7.6 cm)</td></tr><tr class=\"cell\"><td class=\"txt\"> Height </td><td>4.500 in (11.4 cm)</td></tr><tr class=\"alt\"><td class=\"txtb\">Weight </td><td class=\"txt\">2 lb (1 kg)</td></tr> </table>","imgbase":"https://www.capovani.com/clientresources/","imgMain":"107/108/63/563/148799-a-MKS_122A-11063_main_i148799.jpg","imagesXtra":["107/108/63/563/148799-1-MKS_122A-11063_large_i148799.jpg","107/108/63/563/148799-2-MKS_122A-11063_detail1_i148799.jpg"]}