{"itemno":151365,"headline":"ENI POWER SYSTEMS RF GENERATOR 1250W, 13.56 MHZ","description":"Radio Frequency Generator","mfr":"ENI ","model":"OEM 12A","price":"Best Price","qty":3,"location":"Scotia, NY US","category":"Radio Frequency (RF) Generators","keywords":"RF Power Supplies generators plasma","unixTimeStamp":1349361774,"popular":5,"isFeatured":0,"categories.lvl0":"Test & Measurement Equipment","categories.lvl1":"Test & Measurement Equipment > Power Supplies","categories.lvl2":"Test & Measurement Equipment  >  Power Supplies > Radio Frequency (RF) Generators","specstable":"<table border=\"0\" cellpadding=\"2\"><tr class=\"cell\"><td class=\"txtb\">Manufacturer </td><td class=\"txt\">ENI </td></tr><tr class=\"alt\"><td class=\"txtb\">Model </td><td class=\"txt\">OEM 12A </td></tr><tr class=\"cell\"><td class=\"txtb\">Description </td><td class=\"txt\">Radio Frequency Generator </td></tr><tr class=\"alt\"><td class=\"txtb\">Rated Power Output </td><td class=\"txt\">1250 Watts</td></tr><tr class=\"cell\"><td class=\"txtb\">Frequency </td><td class=\"txt\">13.56</td></tr><tr class=\"alt\"><td class=\"txtb\">Scale </td><td class=\"txt\">MHz</td></tr><tr class=\"cell\"><td class=\"txtb\">Output Impedance </td><td class=\"txt\">50 Ohms</td></tr><tr class=\"alt\"><td class=\"txtb\">Reflected Power Limit </td><td class=\"txt\">300.00 W</td></tr><tr class=\"cell\"><td class=\"txtb\">Output Connector </td><td class=\"txt\">Type N</td></tr><tr class=\"alt\"><td class=\"txtb\">Panel Meters </td><td class=\"txt\">Analog</td></tr><tr class=\"cell\"><td class=\"txtb\">External Cooling </td><td class=\"txt\">Water Cooled</td></tr><tr class=\"alt\"><td class=\"txtb\">Other Information </td><td class=\"txt\"><p>Full model number: OEM 12A-21041-51<br />Analog 25 pin SUB-D I/O connector<br /><br /></p></td></tr><tr class=\"cell\" ><td class=\"txtb\">Power Requirements </td><td class=\"txt\">200-240 V 20.0 A 60 Hz 1 Phase</td></tr><tr class=\"alt\" ><td class=\"txtb\">Exterior Dimensions </td><td> </td></tr><tr class=\"cell\"><td class=\"txt\"> Width </td><td>17.000 in (43.2 cm)</td></tr><tr class=\"alt\"><td class=\"txt\"> Depth </td><td>15.750 in (40.0 cm)</td></tr><tr class=\"cell\"><td class=\"txt\"> Height </td><td>8.750 in (22.2 cm)</td></tr><tr class=\"alt\"><td class=\"txtb\">Weight </td><td class=\"txt\">126 lb (57 kg)</td></tr> </table>","imgbase":"https://www.capovani.com/clientresources/","imgMain":"107/108/99/999/151365-a-ENI-Power-Systems-OEM-12A-RF-Generator-1.jpg","imagesXtra":["107/108/99/999/151365-1-ENI-Power-Systems-OEM-12A-RF-Generator-1.jpg","107/108/99/999/151365-2-ENI-Power-Systems-OEM-12A-RF-Generator-2.jpg","107/108/99/999/151365-3-ENI-Power-Systems-OEM-12A-RF-Generator-3.jpg"]}