{"itemno":163510,"headline":"MKS MICRO PIRANI/ABSOLUTE PIEZO TRANSDUCER","description":"Micro Pirani /Absolute Piezo Transducer","mfr":"MKS Instruments","model":"910-42","price":"$282.00","qty":1,"location":"Scotia, NY US","category":"Combination Gauges","keywords":"","unixTimeStamp":1391092755,"popular":1,"isFeatured":1,"specstable":"<table border=\"0\" cellpadding=\"2\"><tr class=\"cell\"><td class=\"txtb\">Manufacturer </td><td class=\"txt\">MKS Instruments</td></tr><tr class=\"alt\"><td class=\"txtb\">Model </td><td class=\"txt\">910-42 </td></tr><tr class=\"cell\"><td class=\"txtb\">Description </td><td class=\"txt\">Micro Pirani /Absolute Piezo Transducer </td></tr><tr class=\"alt\"><td class=\"txtb\">Other Information </td><td class=\"txt\"><p>Range: 1.0 X 10-5 to 1500 Torr<br />Flange: 4 VCR (.25\")<br />Supply: 9-30 VDC<br />Output: 1-9 VDC<br />RS485</p></td></tr><tr class=\"cell\" ><td class=\"txtb\">Exterior Dimensions </td><td> </td></tr><tr class=\"alt\"><td class=\"txt\"> Width </td><td>1.500 in (3.8 cm)</td></tr><tr class=\"cell\"><td class=\"txt\"> Height </td><td>5.500 in (14.0 cm)</td></tr><tr class=\"alt\"><td class=\"txtb\">Weight </td><td class=\"txt\">1 lb (0 kg)</td></tr> </table>","imgbase":"https://www.capovani.com/clientresources/","imgMain":"107/108/95/5595/163510-a-MKS-910-42_I163510.jpg","imagesXtra":["107/108/95/5595/163510-1-MKS-910-42_I163510.jpg"]}