{"itemno":169512,"headline":"YAMATO MECHANICAL CONVECTION OVEN, 200°C","description":"Mechanical Convection Oven","mfr":"Yamato","model":"DN-83","price":"Best Price","qty":1,"location":"Scotia, NY US","category":"Mechanical Convection Ovens","keywords":"forced air drying convection mechanical","unixTimeStamp":1412788537,"popular":8,"isFeatured":0,"categories.lvl0":"Heating & Cooling","categories.lvl1":"Heating & Cooling > Ovens","categories.lvl2":"Heating & Cooling  >  Ovens > Mechanical Convection Ovens","specstable":"<table border=\"0\" cellpadding=\"2\"><tr class=\"cell\"><td class=\"txtb\">Manufacturer </td><td class=\"txt\">Yamato</td></tr><tr class=\"alt\"><td class=\"txtb\">Model </td><td class=\"txt\">DN-83 </td></tr><tr class=\"cell\"><td class=\"txtb\">Maximum Temperature </td><td class=\"txt\">200 ºC (392 ºF, 473 ºK)</td></tr><tr class=\"alt\"><td class=\"txtb\">Minimum Temperature </td><td class=\"txt\">40 ºC (104 ºF, 313.00 ºK)</td></tr><tr class=\"cell\" ><td class=\"txtb\">Heat/Cool Controls </td><td> </td></tr><tr class=\"alt\"><td class=\"txt\"> Control Type </td><td>Programmable</td></tr><tr class=\"cell\"><td class=\"txtb\">Capacity/Volume Box </td><td class=\"txt\">10.40 cu ft (0.29 cu m)</td></tr><tr class=\"alt\" ><td class=\"txtb\">Chamber Size </td><td> </td></tr><tr class=\"cell\"><td class=\"txt\"> Width </td><td>23.60 in (59.94 cm)</td></tr><tr class=\"alt\"><td class=\"txt\"> Depth </td><td>19.30 in (49.02 cm)</td></tr><tr class=\"cell\"><td class=\"txt\"> Height </td><td>39.40 in (100.08 cm)</td></tr><tr class=\"alt\" ><td class=\"txtb\">Chamber Characteristics </td><td> </td></tr><tr class=\"cell\"><td class=\"txt\"> Chamber Construction </td><td>Stainless Steel </td></tr><tr class=\"alt\"><td class=\"txt\"> Maximum Number of Shelves </td><td>29</td></tr><tr class=\"cell\"><td class=\"txt\"> Number of Shelves Provided </td><td>0</td></tr><tr class=\"alt\"><td class=\"txtb\">Other Information </td><td class=\"txt\"><p>See extended description for more specifications.<br /><br />Temperature controller:<br />PID Control with microprocessor.<br />Battery back-up memory<br />5 programmable programs for special requirements</p></td></tr><tr class=\"cell\"><td class=\"txtb\">Extended Description </td><td class=\"txt\"> Details at <a href=\"/clientresources/107/108/50/350/Obj169512-Yamato_DN-83_Mechanical_Convection_Oven_Specifications.pdf\">Yamato DN-83 Mechanical Convection Oven Specifications.pdf</a></td></tr><tr class=\"alt\" ><td class=\"txtb\">Power Requirements </td><td class=\"txt\">220 V 13.0 A 60 Hz 1 Phase</td></tr><tr class=\"cell\" ><td class=\"txtb\">Exterior Dimensions </td><td> </td></tr><tr class=\"alt\"><td class=\"txt\"> Width </td><td>28.000 in (71.1 cm)</td></tr><tr class=\"cell\"><td class=\"txt\"> Depth </td><td>27.200 in (69.1 cm)</td></tr><tr class=\"alt\"><td class=\"txt\"> Height </td><td>65.400 in (166.1 cm)</td></tr><tr class=\"cell\"><td class=\"txtb\">Weight </td><td class=\"txt\">243 lb (110 kg)</td></tr> </table>","imgbase":"https://www.capovani.com/clientresources/","imgMain":"107/108/50/350/169512-a-Yamato-DN-83-Mechanical-Convection-Oven-1.jpg","imagesXtra":["107/108/50/350/169512-1-Yamato-DN-83-Mechanical-Convection-Oven-1.jpg","107/108/50/350/169512-2-Yamato-DN-83-Mechanical-Convection-Oven-2.jpg","107/108/50/350/169512-3-Yamato-DN-83-Mechanical-Convection-Oven-3.jpg","107/108/50/350/169512-4-Yamato-DN-83-Mechanical-Convection-Oven-4.jpg","107/108/50/350/169512-5-Yamato-DN-83-Mechanical-Convection-Oven-5.jpg","107/108/50/350/169512-6-Yamato-DN-83-Mechanical-Convection-Oven-6.jpg","107/108/50/350/169512-7-Yamato-DN-83-Mechanical-Convection-Oven-7.jpg"]}