{"itemno":172812,"headline":"BOC EDWARDS TIC INSTRUMENT CONTROLLER 3 HEAD","description":"TIC Instrument Controller - 3 Head    TIC can accodomate 3 active gauges and automatically recognizes and controls active gauges including APG100 Pirani, convection, thermocouple, strain, inverted magnetron, wide range and active ion gauges.","mfr":"Edwards","model":"D39700000","price":"$710.00","qty":2,"location":"Scotia, NY US","category":"Multiple Gauge Controllers","keywords":"","unixTimeStamp":1421764683,"popular":3,"isFeatured":1,"specstable":"<table border=\"0\" cellpadding=\"2\"><tr class=\"cell\"><td class=\"txtb\">Manufacturer </td><td class=\"txt\">Edwards</td></tr><tr class=\"alt\"><td class=\"txtb\">Model </td><td class=\"txt\">D39700000 </td></tr><tr class=\"cell\"><td class=\"txtb\">Description </td><td class=\"txt\">TIC Instrument Controller - 3 Head </td></tr><tr class=\"alt\"><td class=\"txtb\">Gauge Types Controlled </td><td class=\"txt\">Pirani, convection, thermocouple, ion and more </td></tr><tr class=\"cell\"><td class=\"txtb\">Cables Included </td><td class=\"txt\">No</td></tr><tr class=\"alt\"><td class=\"txtb\">Other Information </td><td class=\"txt\"><p>Serial interface: RS232<br />60 VA Max</p><p>Will work with the gauge <a href=\"https://www.capovani.com/iinfo.cfm?ItemNo=172793\" target=\"_blank\" rel=\"noopener noreferrer\">https://www.capovani.com/iinfo.cfm?ItemNo=172793</a></p></td></tr><tr class=\"cell\" ><td class=\"txtb\">Power Requirements </td><td class=\"txt\">100-240 V 50/60 Hz</td></tr> </table>","imgbase":"https://www.capovani.com/clientresources/","imgMain":"107/108/50/81250/172812-a-BOC-Edwards-TIC-Instrument-Controller---3-Head.jpg","imagesXtra":["107/108/50/81250/172812-1-BOC-Edwards-TIC-Instrument-Controller---3-Head.jpg","107/108/50/81250/172812-2-BOC-Edwards-TIC-Instrument-Controller---3-Head-2.jpg"]}