{"itemno":181994,"headline":"SORENSEN ELGAR DIRECT CURRENT POWER SUPPLY 80 V, 313A","description":"Programmable DC Power Supply","mfr":"Sorensen","model":"SGA 80 313C-1DAA","price":"Best Price","qty":1,"location":"Scotia, NY US","category":"DC Power Supplies","keywords":"dc","unixTimeStamp":1454082768,"popular":2,"isFeatured":0,"categories.lvl0":"Test & Measurement Equipment","categories.lvl1":"Test & Measurement Equipment > Power Supplies","categories.lvl2":"Test & Measurement Equipment  >  Power Supplies > DC Power Supplies","specstable":"<table border=\"0\" cellpadding=\"2\"><tr class=\"cell\"><td class=\"txtb\">Manufacturer </td><td class=\"txt\">Sorensen</td></tr><tr class=\"alt\"><td class=\"txtb\">Model </td><td class=\"txt\">SGA 80 313C-1DAA </td></tr><tr class=\"cell\"><td class=\"txtb\">Maximum Output Voltage </td><td class=\"txt\">80.00 Volts</td></tr><tr class=\"alt\"><td class=\"txtb\">Maximum Output Current </td><td class=\"txt\">313.00 Amps</td></tr><tr class=\"cell\"><td class=\"txtb\">Maximum Output Power </td><td class=\"txt\">25.00 kW</td></tr><tr class=\"alt\" ><td class=\"txtb\">Regulation Modes </td><td class=\"txt\">Constant Current Constant Voltage</td></tr><tr class=\"cell\"><td class=\"txtb\">Panel Meters </td><td class=\"txt\">Digital</td></tr><tr class=\"alt\"><td class=\"txtb\">Control Type </td><td class=\"txt\">Programmable</td></tr><tr class=\"cell\"><td class=\"txtb\">External Cooling </td><td class=\"txt\">Forced Air Cooled</td></tr><tr class=\"alt\"><td class=\"txtb\">Other Information </td><td class=\"txt\"><p><br />See link below for the manual</p></td></tr><tr class=\"cell\"><td class=\"txtb\">Extended Description </td><td class=\"txt\"> Details at <a href=\"/clientresources/107/108/65/365/Obj181994-SGA_SERIES_OPERATION_MANUAL_M550129-01_rAG.pdf\">SGA_SERIES_OPERATION_MANUAL_M550129-01_rAG.pdf</a></td></tr><tr class=\"alt\" ><td class=\"txtb\">Power Requirements </td><td class=\"txt\">200-240 V 125.0 A 50/60 Hz 3 Phase</td></tr><tr class=\"cell\"><td class=\"txtb\">CE Marked </td><td class=\"txt\">YES</td></tr><tr class=\"alt\" ><td class=\"txtb\">Exterior Dimensions </td><td> </td></tr><tr class=\"cell\"><td class=\"txt\"> Width </td><td>19.000 in (48.3 cm)</td></tr><tr class=\"alt\"><td class=\"txt\"> Depth </td><td>29.000 in (73.7 cm)</td></tr><tr class=\"cell\"><td class=\"txt\"> Height </td><td>10.500 in (26.7 cm)</td></tr><tr class=\"alt\"><td class=\"txtb\">Weight </td><td class=\"txt\">140 lb (64 kg)</td></tr> </table>","imgbase":"https://www.capovani.com/clientresources/","imgMain":"107/108/65/365/181994-a-Sorensen-SGA-80-313C-1DAA-DC-Power-Supply-1.jpg","imagesXtra":["107/108/65/365/181994-1-Sorensen-SGA-80-313C-1DAA-DC-Power-Supply-1.jpg","107/108/65/365/181994-2-Sorensen-SGA-80-313C-1DAA-DC-Power-Supply-2.jpg","107/108/65/365/181994-3-Sorensen-SGA-80-313C-1DAA-DC-Power-Supply-3.jpg","107/108/65/365/181994-4-Sorensen-SGA-80-313C-1DAA-DC-Power-Supply-4.jpg"]}