{"itemno":195049,"headline":"TERRA UNIVERSAL FOUR PORT GLOVE BOX SDPVC","description":"Four Port Glove Box with Air Lock   Static Dissapative PVC Construction   Dual Puge and Niro Watch","mfr":"Terra Universal Inc.","model":"3305-10E, 1680-81B","price":"$3,250.00","qty":1,"location":"Scotia, NY US","category":"Glove Boxes","keywords":"old dry box antichamber Chambers  Anaerobic","unixTimeStamp":1509376007,"popular":0,"isFeatured":0,"categories.lvl0":"Laboratory Equipment","categories.lvl1":"Laboratory Equipment > Glove Boxes","specstable":"<table border=\"0\" cellpadding=\"2\"><tr class=\"cell\"><td class=\"txtb\">Manufacturer </td><td class=\"txt\">Terra Universal Inc.</td></tr><tr class=\"alt\"><td class=\"txtb\">Model </td><td class=\"txt\">3305-10E, 1680-81B </td></tr><tr class=\"cell\"><td class=\"txtb\">Number of Stations </td><td class=\"txt\">Two</td></tr><tr class=\"alt\"><td class=\"txtb\">Interior Construction </td><td class=\"txt\">SDPVC </td></tr><tr class=\"cell\"><td class=\"txtb\">Accessories </td><td class=\"txt\"><strong>Dual Puge--Model: 1603-57</strong><br /><p>The Dual Purge System delivers a variable nitrogen purge into the glove box. During normal operation, it provides a continuous low-flow purge to maintain a positive pressure that blocks out contaminants. In the event of a sudden pressure drop, it activates a high-flow purge to block out contaminants and to quickly purge any moisture or contaminants that do enter the chamber.</p><p><strong>Nitro Watch Model: 9500-00A</strong></p><p>The NitroWatch provides automatic low-humidity control. It monitors the internal relative humidity and activates the high-flow purge when the moisture climbs above an adjustable set point. The Automatic RB(Relief/Bleed) Valve provides safe pressure relief with these control systems and also functions as a check valve, ensuring that no moisture or contaminants enter the chamber in the event of a negative pressure. All glove boxes feature a tapped 0.125\" NPT inlet and a 0.25\" NPT outlet for connection to these controls.</p><div><strong>Twin Flouresent Light Bar<br /><br />Stainless Steel Work Surface</strong></div></td></tr><tr class=\"alt\"><td class=\"txtb\">Other Information </td><td class=\"txt\"><strong>Glovebox Details</strong><br />Length: 59\"<br />Depth: 24\"<br />Height: 24\"<br />Distance beween gloves\" 15\"<br />Distance from base to gloves center: 10\"<br />Glove port diameter: 10\"<br />Airlock Left Side: 24\" L x 10\" x 10\"<br />Airlock Right Side: 10\" x 10\" x 10\"<br /><br />Overall Length including airlocks: 96\"<br /><br /><strong>NB: Gloves not included</strong></td></tr><tr class=\"cell\" ><td class=\"txtb\">Power Requirements </td><td class=\"txt\">120/220 V 50/60 Hz 1 Phase</td></tr><tr class=\"alt\"><td class=\"txtb\">CE Marked </td><td class=\"txt\">YES</td></tr><tr class=\"cell\" ><td class=\"txtb\">Exterior Dimensions </td><td> </td></tr><tr class=\"alt\"><td class=\"txt\"> Width </td><td>96.000 in (243.8 cm)</td></tr><tr class=\"cell\"><td class=\"txt\"> Depth </td><td>24.000 in (61.0 cm)</td></tr><tr class=\"alt\"><td class=\"txt\"> Height </td><td>24.000 in (61.0 cm)</td></tr> </table>","imgbase":"https://www.capovani.com/clientresources/","imgMain":"107/108/71/571/195049-a-Terra-Universal-3305-10E-Four-Port-Glove-Box-1.jpg","imagesXtra":["107/108/71/571/195049-1-Terra-Universal-3305-10E-Four-Port-Glove-Box-1.jpg","107/108/71/571/195049-2-Terra-Universal-3305-10E-Four-Port-Glove-Box-2.jpg","107/108/71/571/195049-3-Terra-Universal-3305-10E-Four-Port-Glove-Box-3.jpg","107/108/71/571/195049-4-Terra-Universal-3305-10E-Four-Port-Glove-Box-4.jpg","107/108/71/571/195049-5-Terra-Universal-3305-10E-Four-Port-Glove-Box-5.jpg","107/108/71/571/195049-6-Terra-Universal-3305-10E-Four-Port-Glove-Box-6.jpg","107/108/71/571/195049-7-Terra-Universal-3305-10E-Four-Port-Glove-Box-7.jpg","107/108/71/571/195049-8-Terra-Universal-3305-10E-Four-Port-Glove-Box-8.jpg","107/108/71/571/195049-9-Terra-Universal-3305-10E-Four-Port-Glove-Box-9.jpg","107/108/71/571/195049-10-Terra-Universal-3305-10E-Four-Port-Glove-Box-10.jpg","107/108/71/571/195049-11-Terra-Universal-3305-10E-Four-Port-Glove-Box-11.jpg","107/108/71/571/195049-12-Terra-Universal-3305-10E-Four-Port-Glove-Box-12.jpg","107/108/71/571/195049-13-Terra-Universal-3305-10E-Four-Port-Glove-Box-13.jpg","107/108/71/571/195049-14-Terra-Universal-3305-10E-Four-Port-Glove-Box-14.jpg"]}