{"itemno":196929,"headline":"PFEIFFER TURBO PUMP CABLE 3.5M","description":"Turbo Pump Cable for ATH Series Pump","mfr":"Pfeiffer Vacuum","model":"A215300-035","price":"Best Price","qty":2,"location":"Scotia, NY US","category":"Vacuum Pump Accessories","keywords":"filters cables clamps controllers","unixTimeStamp":1519313699,"popular":0,"isFeatured":0,"categories.lvl0":"Vacuum Processing Equipment","categories.lvl1":"Vacuum Processing Equipment > Vacuum Pumps","categories.lvl2":"Vacuum Processing Equipment  >  Vacuum Pumps > Vacuum Pump Accessories","specstable":"<table border=\"0\" cellpadding=\"2\"><tr class=\"cell\"><td class=\"txtb\">Manufacturer </td><td class=\"txt\">Pfeiffer Vacuum</td></tr><tr class=\"alt\"><td class=\"txtb\">Model </td><td class=\"txt\">A215300-035 </td></tr><tr class=\"cell\"><td class=\"txtb\">Description </td><td class=\"txt\">Cable [INVALID] Turbo Pump 3.5M </td></tr><tr class=\"alt\"><td class=\"txtb\">Other Information </td><td class=\"txt\">Part No.: A215300-035</td></tr> </table>","imgbase":"https://www.capovani.com/clientresources/","imgMain":"107/108/90/83390/196929-a-Pfeiffer-A215300-035-Turbo-Pump-Cable--1.jpg","imagesXtra":["107/108/90/83390/196929-1-Pfeiffer-A215300-035-Turbo-Pump-Cable--1.jpg","107/108/90/83390/196929-2-Pfeiffer-A215300-035-Turbo-Pump-Cable--2.jpg"]}