{"itemno":206058,"headline":"YIELD ENGINEERING HMDS VAPOR PRIME OVEN","description":"HMDS Vapor Prime / Image Reversal / Silylation Processing Oven","mfr":"Yield Engineerng Sys","model":"YES 58SM","price":"Best Price","qty":1,"location":"Scotia, NY US","category":"Other Ovens","keywords":"special custom vacuum pressure","unixTimeStamp":1559122172,"popular":2,"isFeatured":0,"categories.lvl0":"Heating & Cooling","categories.lvl1":"Heating & Cooling > Ovens","categories.lvl2":"Heating & Cooling  >  Ovens > Other Ovens","specstable":"<table border=\"0\" cellpadding=\"2\"><tr class=\"cell\"><td class=\"txtb\">Manufacturer </td><td class=\"txt\">Yield Engineerng Sys</td></tr><tr class=\"alt\"><td class=\"txtb\">Model </td><td class=\"txt\">YES 58SM </td></tr><tr class=\"cell\"><td class=\"txtb\">Description </td><td class=\"txt\">HMDS Vapor Prime / Image Reversal / Silylation </td></tr><tr class=\"alt\"><td class=\"txtb\">Maximum Temperature </td><td class=\"txt\">275 ºC (527 ºF, 548 ºK)</td></tr><tr class=\"cell\" ><td class=\"txtb\">Temperature Control </td><td> </td></tr><tr class=\"alt\"><td class=\"txt\"> Control Stability </td><td>± 2.000 ºC</td></tr><tr class=\"cell\" ><td class=\"txtb\">Heat/Cool Controls </td><td> </td></tr><tr class=\"alt\"><td class=\"txt\"> Control Type </td><td>Other</td></tr><tr class=\"cell\" ><td class=\"txtb\">Chamber Size </td><td> </td></tr><tr class=\"alt\"><td class=\"txt\"> Width </td><td>16.00 in (40.64 cm)</td></tr><tr class=\"cell\"><td class=\"txt\"> Depth </td><td>16.00 in (40.64 cm)</td></tr><tr class=\"alt\"><td class=\"txt\"> Height </td><td>16.00 in (40.64 cm)</td></tr><tr class=\"cell\" ><td class=\"txtb\">Chamber Characteristics </td><td> </td></tr><tr class=\"alt\"><td class=\"txt\"> Chamber Construction </td><td>Stainless Steel </td></tr><tr class=\"cell\"><td class=\"txt\"> Maximum Number of Shelves </td><td>1</td></tr><tr class=\"alt\"><td class=\"txtb\">Other Information </td><td class=\"txt\"><p>Capacity: 6\" Wafers, (4) Cassettes, 4\" Wafers (6) Cassettes</p></td></tr><tr class=\"cell\" ><td class=\"txtb\">Power Requirements </td><td class=\"txt\">120 V 20.0 A 50/60 Hz 1 Phase</td></tr> </table>","imgbase":"https://www.capovani.com/clientresources/","imgMain":"107/108/55/555/206058-a-Yield-Engineering-YES-58SM-HMDS-Oven-1.jpg","imagesXtra":["107/108/55/555/206058-1-Yield-Engineering-YES-58SM-HMDS-Oven-1.jpg","107/108/55/555/206058-2-Yield-Engineering-YES-58SM-HMDS-Oven-2.jpg","107/108/55/555/206058-3-Yield-Engineering-YES-58SM-HMDS-Oven-3.jpg","107/108/55/555/206058-4-Yield-Engineering-YES-58SM-HMDS-Oven-4.jpg","107/108/55/555/206058-5-Yield-Engineering-YES-58SM-HMDS-Oven-5.jpg","107/108/55/555/206058-6-Yield-Engineering-YES-58SM-HMDS-Oven-6.jpg","107/108/55/555/206058-7-Yield-Engineering-YES-58SM-HMDS-Oven-7.jpg","107/108/55/555/206058-8-Yield-Engineering-YES-58SM-HMDS-Oven-8.jpg","107/108/55/555/206058-9-Yield-Engineering-YES-58SM-HMDS-Oven-9.jpg","107/108/55/555/206058-10-Yield-Engineering-YES-58SM-HMDS-Oven-10.jpg","107/108/55/555/206058-11-Yield-Engineering-YES-58SM-HMDS-Oven-11.jpg","107/108/55/555/206058-12-Yield-Engineering-YES-58SM-HMDS-Oven-12.jpg","107/108/55/555/206058-13-Yield-Engineering-YES-58SM-HMDS-Oven-13.jpg","107/108/55/555/206058-14-Yield-Engineering-YES-58SM-HMDS-Oven-14.jpg"]}