{"itemno":209568,"headline":"CTI CRYOGENICS CRYOGENIC VACUUM PUMP 10,000 L/S AIR","description":"Cryo Pump - Remanufactured","mfr":"CTI Cryogenics","model":"CRYO-TORR 500","price":"Best Price","qty":1,"location":"Scotia, NY US","category":"Cryopumps","keywords":"cryogenci vacuum pumps  cryo pumps  cryos  helium pumps","unixTimeStamp":1574685329,"popular":1,"isFeatured":0,"categories.lvl0":"Vacuum Processing Equipment","categories.lvl1":"Vacuum Processing Equipment > Vacuum Pumps","categories.lvl2":"Vacuum Processing Equipment  >  Vacuum Pumps > Cryopumps","specstable":"<table border=\"0\" cellpadding=\"2\"><tr class=\"cell\"><td class=\"txtb\">Manufacturer </td><td class=\"txt\">CTI Cryogenics</td></tr><tr class=\"alt\"><td class=\"txtb\">Model </td><td class=\"txt\">CRYO-TORR 500 </td></tr><tr class=\"cell\" ><td class=\"txtb\">Inlet Flange </td><td class=\"txt\">ASA 711.2 mm (28.000 in)</td></tr><tr class=\"alt\" ><td class=\"txtb\">Foreline Flange </td><td class=\"txt\">KF 25.0 mm (0.984 in)</td></tr><tr class=\"cell\"><td class=\"txtb\">Pumping Speed Water Vapor </td><td class=\"txt\">30,000.00 l/s (63,572.79 CFM)</td></tr><tr class=\"alt\"><td class=\"txtb\">Pumping Speed Air </td><td class=\"txt\">10,000.00 l/s (21,190.93 CFM)</td></tr><tr class=\"cell\"><td class=\"txtb\">Other Information </td><td class=\"txt\"><p>20 bolt ASA ANSI Flange</p><p>Remanufactured in March 2020</p></td></tr><tr class=\"alt\"><td class=\"txtb\">Extended Description </td><td class=\"txt\"> Details at <a href=\"/clientresources/107/108/46/146/Obj209568-CTI_Cryo_Torr_500_Specs.pdf\">CTI Cryo Torr 500 Specs.pdf</a></td></tr><tr class=\"cell\"><td class=\"txtb\">CE Marked </td><td class=\"txt\">YES</td></tr> </table>","imgbase":"https://www.capovani.com/clientresources/","imgMain":"107/108/46/146/209568-a-CTI-Cryogenics-Cryo-Torr-500--001.jpg","imagesXtra":["107/108/46/146/209568-1-CTI-Cryogenics-Cryo-Torr-500--001.jpg","107/108/46/146/209568-2-CTI-Cryogenics-Cryo-Torr-500--002.jpg","107/108/46/146/209568-3-CTI-Cryogenics-Cryo-Torr-500--003.jpg","107/108/46/146/209568-4-CTI-Cryogenics-Cryo-Torr-500--004.jpg"]}