{"itemno":2634,"headline":"KEY HIGH VACUUM PRODUCTS MOLECULAR SIEVE FORELINE TRAP","description":"Molecular Sieve Foreline Trap    Offers an extremely effective method for preventing   backstreaming of mechanical roughing pump oils","mfr":"Key High Vacuum","model":"MT300","price":"$275.00","qty":1,"location":"Scotia, NY US","category":"Other Vacuum Equipment","keywords":"components system components supplies","unixTimeStamp":992435760,"popular":1,"isFeatured":0,"categories.lvl0":"Vacuum Processing Equipment","categories.lvl1":"Vacuum Processing Equipment > Other Vacuum Equipment","specstable":"<table border=\"0\" cellpadding=\"2\"><tr class=\"cell\"><td class=\"txtb\">Manufacturer </td><td class=\"txt\">Key High Vacuum</td></tr><tr class=\"alt\"><td class=\"txtb\">Model </td><td class=\"txt\">MT300 </td></tr><tr class=\"cell\"><td class=\"txtb\">Description </td><td class=\"txt\">Trap, Molecular Sieve, Foreline </td></tr><tr class=\"alt\"><td class=\"txtb\">Other Information </td><td class=\"txt\"><ul><li>In and out tubes both 3\" OD (tubulation \"flange\")</li><li>Chamber filled with synthetic Zeolite sieve material<br /> (sorptive capability is renewed by baking)</li><li>High absorption rate for oil and water vapors</li><li>Includes internal sieve reactivation heater</li><li>Constructed entirely of 304 stainless steel</li></ul></td></tr><tr class=\"cell\"><td class=\"txtb\">Condition </td><td class=\"txt\">Like New</td></tr><tr class=\"alt\"><td class=\"txtb\">Weight </td><td class=\"txt\">12 lb (5 kg)</td></tr> </table>","imgbase":"https://www.capovani.com/clientresources/","imgMain":"107/108/83/63183/2634-a_KeyHighVacuum_MT-300_i2634_143w200h.jpg","imagesXtra":[]}