{"itemno":3983,"headline":"UTHE 20E","description":"Ultrasonic Generator","mfr":"Uthe","model":"20E","price":"$500.00","qty":1,"location":"Scotia, NY US","category":"Other Wire Bonding Equipment","keywords":"wire bonders  bonder  wedge bonder  wire bonder","unixTimeStamp":1008599280,"popular":1,"isFeatured":0,"specstable":"<table border=\"0\" cellpadding=\"2\"><tr class=\"cell\"><td class=\"txtb\">Manufacturer </td><td class=\"txt\">Uthe</td></tr><tr class=\"alt\"><td class=\"txtb\">Model </td><td class=\"txt\">20E </td></tr><tr class=\"cell\"><td class=\"txtb\">Description </td><td class=\"txt\">Ultrasonic Generator </td></tr><tr class=\"alt\"><td class=\"txtb\">Other Information </td><td class=\"txt\">Formerly item 1857<br>Frequency 55 to 64 kHz<br>Time range 5 to 100 mil/sec<br>Timer stability 1 %<br>Bonder motors 1.8 to 250 V<br>Wire size 1.0 to 15 mil gold or alum.<br>Compatable with all UTHE piezo transducers<br>Power output 0.2 to 2.0 W</td></tr><tr class=\"cell\"><td class=\"txtb\">Condition </td><td class=\"txt\">Very Good</td></tr><tr class=\"alt\"><td class=\"txtb\">Weight </td><td class=\"txt\">14 lb (6 kg)</td></tr><tr class=\"cell\" ><td class=\"txtb\">Exterior Dimensions </td><td> </td></tr><tr class=\"alt\"><td class=\"txt\"> Width </td><td>12.000 in (30.5 cm)</td></tr><tr class=\"cell\"><td class=\"txt\"> Depth </td><td>10.500 in (26.7 cm)</td></tr><tr class=\"alt\"><td class=\"txt\"> Height </td><td>3.500 in (8.9 cm)</td></tr> </table>","imgbase":"https://www.capovani.com/clientresources/","imgMain":"107/108/73/84373/3983-a-Uthe_20E_main_i3983.jpg","imagesXtra":["107/108/73/84373/3983-1-Uthe_20E_large_i3983.jpg","107/108/73/84373/3983-2-Uthe_20E_detail_i3983.jpg"]}