{"itemno":39847,"headline":"INFRANOR SMTBD1-220/30-TBS-DP","description":"Servo Controller","mfr":"Infranor","model":"SMTBD1-220/30-TBS-DP","price":"$1,650.00","qty":7,"location":"Scotia, NY US","category":"Positioning Controllers","keywords":"","unixTimeStamp":1103022298,"popular":5,"isFeatured":0,"categories.lvl0":"Optical / Photonic Equipment","categories.lvl1":"Optical / Photonic Equipment > Positioning Equipment","categories.lvl2":"Optical / Photonic Equipment  >  Positioning Equipment > Positioning Controllers","specstable":"<table border=\"0\" cellpadding=\"2\"><tr class=\"cell\"><td class=\"txtb\">Manufacturer </td><td class=\"txt\">Infranor</td></tr><tr class=\"alt\"><td class=\"txtb\">Model </td><td class=\"txt\">SMTBD1-220/30-TBS-DP </td></tr><tr class=\"cell\"><td class=\"txtb\">Description </td><td class=\"txt\">Servo Controller </td></tr><tr class=\"alt\" ><td class=\"txtb\">Power Requirements </td><td class=\"txt\">220 V</td></tr><tr class=\"cell\"><td class=\"txtb\">CE Marked </td><td class=\"txt\">YES</td></tr><tr class=\"alt\" ><td class=\"txtb\">Exterior Dimensions </td><td> </td></tr><tr class=\"cell\"><td class=\"txt\"> Width </td><td>2.500 in (6.4 cm)</td></tr><tr class=\"alt\"><td class=\"txt\"> Depth </td><td>11.500 in (29.2 cm)</td></tr><tr class=\"cell\"><td class=\"txt\"> Height </td><td>11.500 in (29.2 cm)</td></tr><tr class=\"alt\"><td class=\"txtb\">Weight </td><td class=\"txt\">8 lb (4 kg)</td></tr> </table>","imgbase":"https://www.capovani.com/clientresources/","imgMain":"107/108/92/992/39847-a_Infranor_SMTBD1-220-30-TBS-DP_main_i39847.jpg","imagesXtra":["107/108/92/992/39847-1_Infranor_SMTBD1-220-30-TBS-DP_large_i39847.jpg"]}