{"itemno":46789,"headline":"NEWPORT 860Scc","description":"Positioning Controller","mfr":"Newport","model":"860Scc","price":"$350.00","qty":7,"location":"Scotia, NY US","category":"Positioning Controllers","keywords":"","unixTimeStamp":1117021586,"popular":4,"isFeatured":0,"categories.lvl0":"Optical / Photonic Equipment","categories.lvl1":"Optical / Photonic Equipment > Positioning Equipment","categories.lvl2":"Optical / Photonic Equipment  >  Positioning Equipment > Positioning Controllers","specstable":"<table border=\"0\" cellpadding=\"2\"><tr class=\"cell\"><td class=\"txtb\">Manufacturer </td><td class=\"txt\">Newport</td></tr><tr class=\"alt\"><td class=\"txtb\">Model </td><td class=\"txt\">860Scc </td></tr><tr class=\"cell\"><td class=\"txtb\">Description </td><td class=\"txt\">Positioning Controller </td></tr><tr class=\"alt\"><td class=\"txtb\">Accessories </td><td class=\"txt\"><p><br />Actuators sold separately, <a href=\"http://www.capovani.com/iinfo.cfm?ItemNo=4539\" target=\"_blank\" rel=\"noopener noreferrer\">click here for 25 mm travel actuator<br /></a></p></td></tr><tr class=\"cell\" ><td class=\"txtb\">Power Requirements </td><td class=\"txt\">115 V 50/60 Hz 1 Phase</td></tr><tr class=\"alt\"><td class=\"txtb\">Condition </td><td class=\"txt\">Very Good</td></tr><tr class=\"cell\" ><td class=\"txtb\">Exterior Dimensions </td><td> </td></tr><tr class=\"alt\"><td class=\"txt\"> Width </td><td>6.500 in (16.5 cm)</td></tr><tr class=\"cell\"><td class=\"txt\"> Depth </td><td>4.750 in (12.1 cm)</td></tr><tr class=\"alt\"><td class=\"txt\"> Height </td><td>3.250 in (8.3 cm)</td></tr><tr class=\"cell\"><td class=\"txtb\">Weight </td><td class=\"txt\">1 lb (0 kg)</td></tr> </table>","imgbase":"https://www.capovani.com/clientresources/","imgMain":"107/108/92/992/46789-a_Newport_860Scc_main_i46789.jpg","imagesXtra":["107/108/92/992/46789-1_Newport_860Scc_large_i46789.jpg"]}