{"itemno":85139,"headline":"HUNTINGTON BUTTERFLY VACUUM VALVE KF 50 MM","description":"Butterfly Vacuum Valve","mfr":"Huntington","model":"BF-200-SF","price":"$345.00","qty":2,"location":"Scotia, NY US","category":"Vacuum Butterfly Valves","keywords":"","unixTimeStamp":1185987264,"popular":2,"isFeatured":0,"specstable":"<table border=\"0\" cellpadding=\"2\"><tr class=\"cell\"><td class=\"txtb\">Manufacturer </td><td class=\"txt\">Huntington</td></tr><tr class=\"alt\"><td class=\"txtb\">Model </td><td class=\"txt\">BF-200-SF </td></tr><tr class=\"cell\"><td class=\"txtb\">Valve Actuation </td><td class=\"txt\">Manual</td></tr><tr class=\"alt\"><td class=\"txtb\">Flange Type </td><td class=\"txt\">KF</td></tr><tr class=\"cell\"><td class=\"txtb\">Flange Size </td><td class=\"txt\">50.00 mm (1.97 in)</td></tr><tr class=\"alt\"><td class=\"txtb\">Valve Material </td><td class=\"txt\">Stainless Steel</td></tr><tr class=\"cell\" ><td class=\"txtb\">Exterior Dimensions </td><td> </td></tr><tr class=\"alt\"><td class=\"txt\"> Width </td><td>3.500 in (8.9 cm)</td></tr><tr class=\"cell\"><td class=\"txt\"> Depth </td><td>2.500 in (6.4 cm)</td></tr><tr class=\"alt\"><td class=\"txt\"> Height </td><td>5.000 in (12.7 cm)</td></tr><tr class=\"cell\"><td class=\"txtb\">Weight </td><td class=\"txt\">2 lb (1 kg)</td></tr> </table>","imgbase":"https://www.capovani.com/clientresources/","imgMain":"107/108/22/1622/85139-a_Huntington_BF-200-SF_main_i85139.jpg","imagesXtra":["107/108/22/1622/85139-1_Huntington_BF-200-SF_large_i85139.jpg"]}