{"itemno":85191,"headline":"SMC VACUUM ANGLE VALVE, 4 INCH","description":"Vacuum Angle Valve","mfr":"SMC","model":"XLA-100","price":"$1,270.00","qty":1,"location":"Scotia, NY US","category":"Vacuum Angle Valves","keywords":"","unixTimeStamp":1186048713,"popular":2,"isFeatured":0,"specstable":"<table border=\"0\" cellpadding=\"2\"><tr class=\"cell\"><td class=\"txtb\">Manufacturer </td><td class=\"txt\">SMC</td></tr><tr class=\"alt\"><td class=\"txtb\">Model </td><td class=\"txt\">XLA-100 </td></tr><tr class=\"cell\"><td class=\"txtb\">Valve Angle </td><td class=\"txt\">90°</td></tr><tr class=\"alt\"><td class=\"txtb\">Valve Actuation </td><td class=\"txt\">Pneumatic</td></tr><tr class=\"cell\"><td class=\"txtb\">Flange Type </td><td class=\"txt\">ISO-K</td></tr><tr class=\"alt\"><td class=\"txtb\">Flange Size </td><td class=\"txt\">101.60 mm (4.00 in)</td></tr><tr class=\"cell\"><td class=\"txtb\">Valve Material </td><td class=\"txt\">Aluminum</td></tr><tr class=\"alt\"><td class=\"txtb\">Position Indicator </td><td class=\"txt\">YES</td></tr><tr class=\"cell\" ><td class=\"txtb\">Exterior Dimensions </td><td> </td></tr><tr class=\"alt\"><td class=\"txt\"> Width </td><td>6.000 in (15.2 cm)</td></tr><tr class=\"cell\"><td class=\"txt\"> Depth </td><td>7.000 in (17.8 cm)</td></tr><tr class=\"alt\"><td class=\"txt\"> Height </td><td>12.000 in (30.5 cm)</td></tr><tr class=\"cell\"><td class=\"txtb\">Weight </td><td class=\"txt\">22 lb (10 kg)</td></tr> </table>","imgbase":"https://www.capovani.com/clientresources/","imgMain":"107/108/21/1621/85191-a_SMC_XLA-100_main_i85191.jpg","imagesXtra":["107/108/21/1621/85191-1_SMC_XLA-100_large_i85191.jpg"]}