{"itemno":93772,"headline":"HEWLETT PACKARD DC POWER SUPPLY 50V, 2A","description":"DC Power Supply","mfr":"Hewlett Packard","model":"6633B","price":"$1,500.00","qty":1,"location":"Scotia, NY US","category":"DC Power Supplies","keywords":"dc","unixTimeStamp":1206457819,"popular":0,"isFeatured":0,"categories.lvl0":"Test & Measurement Equipment","categories.lvl1":"Test & Measurement Equipment > Power Supplies","categories.lvl2":"Test & Measurement Equipment  >  Power Supplies > DC Power Supplies","specstable":"<table border=\"0\" cellpadding=\"2\"><tr class=\"cell\"><td class=\"txtb\">Manufacturer </td><td class=\"txt\">Hewlett Packard</td></tr><tr class=\"alt\"><td class=\"txtb\">Model </td><td class=\"txt\">6633B </td></tr><tr class=\"cell\"><td class=\"txtb\">Maximum Output Voltage </td><td class=\"txt\">50.00 Volts</td></tr><tr class=\"alt\"><td class=\"txtb\">Maximum Output Current </td><td class=\"txt\">2.00 Amps</td></tr><tr class=\"cell\"><td class=\"txtb\">Maximum Output Power </td><td class=\"txt\">0.10 kW</td></tr><tr class=\"alt\" ><td class=\"txtb\">Regulation Modes </td><td class=\"txt\">Constant Current Constant Voltage</td></tr><tr class=\"cell\"><td class=\"txtb\">Panel Meters </td><td class=\"txt\">Digital</td></tr><tr class=\"alt\"><td class=\"txtb\">Interface </td><td class=\"txt\">RS 232</td></tr><tr class=\"cell\"><td class=\"txtb\">Interface 2 </td><td class=\"txt\">IEEE 488-GPIB</td></tr><tr class=\"alt\"><td class=\"txtb\">Control Type </td><td class=\"txt\">Programmable</td></tr><tr class=\"cell\"><td class=\"txtb\">Other Information </td><td class=\"txt\">Programming is done using industry standard SCPI commands via the GPIB or RS-232.</td></tr><tr class=\"alt\" ><td class=\"txtb\">Power Requirements </td><td class=\"txt\">120 V 3.0 A 50/60 Hz 1 Phase</td></tr><tr class=\"cell\"><td class=\"txtb\">CE Marked </td><td class=\"txt\">YES</td></tr><tr class=\"alt\" ><td class=\"txtb\">Exterior Dimensions </td><td> </td></tr><tr class=\"cell\"><td class=\"txt\"> Width </td><td>19.000 in (48.3 cm)</td></tr><tr class=\"alt\"><td class=\"txt\"> Depth </td><td>15.500 in (39.4 cm)</td></tr><tr class=\"cell\"><td class=\"txt\"> Height </td><td>3.500 in (8.9 cm)</td></tr> </table>","imgbase":"https://www.capovani.com/clientresources/","imgMain":"107/108/65/365/93772-a_H.P._6633B_main_i93772.jpg","imagesXtra":["107/108/65/365/93772-1_H.P._6633B_large_i93772.jpg","107/108/65/365/93772-2_H.P._6633B_detail_i93772.jpg"]}